portia/__init__.py
portia/agents/__init__.py
portia/agents/base_agent.py
portia/agents/complex_langgraph_agent.py
portia/agents/context.py
portia/agents/simple_agent.py
portia/agents/toolless_agent.py
portia/clarification.py
portia/cli.py
portia/config.py
portia/errors.py
portia/llm_wrapper.py
portia/plan.py
portia/planner.py
portia/runner.py
portia/storage.py
portia/templates/__init__.py
portia/templates/query_planner.xml.jinja
portia/templates/render.py
portia/templates/tool_description.xml.jinja
portia/tool.py
portia/tool_registry.py
portia/types.py
portia/workflow.py
porita_sdk_python-0.0.1a2.dist-info/LICENSE
porita_sdk_python-0.0.1a2.dist-info/METADATA
porita_sdk_python-0.0.1a2.dist-info/WHEEL
porita_sdk_python-0.0.1a2.dist-info/entry_points.txt
porita_sdk_python-0.0.1a2.dist-info/RECORD
