Metadata-Version: 2.1
Name: porita-sdk-python
Version: 0.0.1a2
Summary: Portia Labs Python SDK for building agentic workflows.
Home-page: https://www.portialabs.ai/
Keywords: LLM,agentic,workflow
Author: Tech
Author-email: tech@portialabs.ai
Requires-Python: >=3.12,<4.0
Classifier: Development Status :: 3 - Alpha
Classifier: Programming Language :: Python :: 3
Classifier: Programming Language :: Python :: 3.12
Classifier: Programming Language :: Python :: 3.13
Requires-Dist: anthropic (>=0.40.0,<0.41.0)
Requires-Dist: click (>=8.1.7,<9.0.0)
Requires-Dist: instructor (>=1.7.0,<2.0.0)
Requires-Dist: jinja2 (>=3.1.4,<4.0.0)
Requires-Dist: langchain (>=0.3.12,<0.4.0)
Requires-Dist: langchain-anthropic (>=0.3.0,<0.4.0)
Requires-Dist: langchain-core (>=0.3.25,<0.4.0)
Requires-Dist: langchain-mistralai (>=0.2.3,<0.3.0)
Requires-Dist: langchain-openai (>=0.2.12,<0.3.0)
Requires-Dist: langgraph (>=0.2.59,<0.3.0)
Requires-Dist: mistralai (>=1.2.5,<2.0.0)
Requires-Dist: pydantic (>=2.10.3,<3.0.0)
Project-URL: Documentation, https://www.portialabs.ai/docs
Project-URL: Repository, https://pypi.org/TomPortia/portia-sdk-python/
